DataExpansion/DatabaseManager.py
DataExpansion/__init__.py
DataExpansion/errorhandler.py
DataExpansion/treining.py
aicluster-1.0.0a1.dist-info/METADATA
aicluster-1.0.0a1.dist-info/WHEEL
aicluster-1.0.0a1.dist-info/top_level.txt
aicluster-1.0.0a1.dist-info/RECORD
