Metadata-Version: 2.1
Name: aicluster
Version: 1.0.0a1
Summary: Um miniframework para facilitar a criação e treinamento de IAs
Home-page: https://github.com/seuusuario/aicluster
Author: Quaghate
Author-email: rsabelha@gmail.com
Classifier: Programming Language :: Python :: 3
Classifier: License :: OSI Approved :: MIT License
Classifier: Operating System :: OS Independent
Requires-Python: >=3.6
Requires-Dist: numpy
Requires-Dist: psutil
Requires-Dist: scikit-learn
Requires-Dist: joblib
Requires-Dist: mysql-connector-python
Requires-Dist: psycopg2
Requires-Dist: faker
Requires-Dist: pandas
Requires-Dist: sentence-transformers
Requires-Dist: tensorflow
Requires-Dist: pyyaml
